Metadata-Version: 2.1
Name: rhasspy-asr-kaldi
Version: 0.1.6
Summary: UNKNOWN
Home-page: https://github.com/rhasspy/rhasspy-asr-kaldi
Author: Michael Hansen
Author-email: hansen.mike@gmail.com
License: UNKNOWN
Platform: UNKNOWN
Classifier: Operating System :: POSIX :: Linux
Classifier: Programming Language :: Python :: 3
Classifier: License :: OSI Approved :: MIT License
Requires-Python: >=3.7
